README.rst
mlflow_observer.py
setup.py
mlflow_observer.egg-info/PKG-INFO
mlflow_observer.egg-info/SOURCES.txt
mlflow_observer.egg-info/dependency_links.txt
mlflow_observer.egg-info/requires.txt
mlflow_observer.egg-info/top_level.txt